pdf2john/__init__.py
pdf2john/pdf2john.py
pdf2john-0.2.0.dist-info/LICENSE.md
pdf2john-0.2.0.dist-info/METADATA
pdf2john-0.2.0.dist-info/WHEEL
pdf2john-0.2.0.dist-info/entry_points.txt
pdf2john-0.2.0.dist-info/RECORD
