Metadata-Version: 2.1
Name: pdf2john
Version: 0.2.0
Summary: A modern refactoring of the legacy pdf2john library
Home-page: https://github.com/benjamin-awd/pdf2john
License: MIT
Author: Benjamin Dornel
Author-email: benjamindornel@gmail.com
Requires-Python: >=3.11,<4.0
Classifier: Development Status :: 3 - Alpha
Classifier: License :: OSI Approved :: MIT License
Classifier: Programming Language :: Python :: 3
Classifier: Programming Language :: Python :: 3.11
Classifier: Programming Language :: Python :: 3.12
Classifier: Topic :: Security
Requires-Dist: pyhanko (>=0.21,<0.24)
Project-URL: Repository, https://github.com/benjamin-awd/pdf2john
